dbscan/__init__.py
dbscan/_dbscan.abi3.so
dbscan-1.0.0.dist-info/WHEEL
dbscan-1.0.0.dist-info/top_level.txt
dbscan-1.0.0.dist-info/RECORD
dbscan-1.0.0.dist-info/METADATA
dbscan-1.0.0.dist-info/licenses/LICENSE
