Metadata-Version: 2.4
Name: dbscan
Version: 1.0.0
Summary: Theoretically efficient and practical parallel DBSCAN
Home-page: https://github.com/wangyiqiu/dbscan-python
Author: Yiqiu Wang
Author-email: Yiqiu Wang <yiqiuwang.work@gmail.com>
Maintainer-email: Anirudh Vegesana <avegesan@cs.stanford.edu>
License: MIT
Project-URL: homepage, https://sites.google.com/view/yiqiuwang/dbscan
Project-URL: repository, https://github.com/wangyiqiu/dbscan-python
Keywords: cluster,clustering,density,dbscan
Classifier: Development Status :: 4 - Beta
Classifier: Intended Audience :: Science/Research
Classifier: Intended Audience :: Developers
Classifier: License :: OSI Approved :: MIT License
Classifier: Programming Language :: C++
Classifier: Programming Language :: Python :: 3.9
Classifier: Programming Language :: Python :: 3.10
Classifier: Programming Language :: Python :: 3.11
Classifier: Programming Language :: Python :: 3.12
Classifier: Operating System :: POSIX :: Linux
Classifier: Operating System :: MacOS
Classifier: Topic :: Software Development
Classifier: Topic :: Scientific/Engineering
Requires-Python: >=3.12,<4
License-File: LICENSE
Requires-Dist: numpy>=2.0.0
Requires-Dist: scikit-learn>=1.0
Provides-Extra: example
Requires-Dist: matplotlib; extra == "example"
Dynamic: author
Dynamic: home-page
Dynamic: license-file
Dynamic: requires-python
